{
  "name": "ParticipanteCurso",
  "base": "PersistedModel",
  "idInjection": false,
  "options": {
    "validateUpsert": true
  },
  "postgresql": {
    "schema": "encuestas",
    "table": "participante_curso"
  },
  "properties": {
    "id": {
      "type": "Number",
      "id": true,
      "required": false,
      "length": null,
      "precision": 64,
      "scale": 0,
      "postgresql": {
        "columnName": "id",
        "dataType": "bigint",
        "dataLength": null,
        "dataPrecision": 64,
        "dataScale": 0,
        "nullable": "NO"
      },
      "_selectable": false
    },
    "idInscripcionCurso": {
      "type": "Number",
      "required": false,
      "length": null,
      "precision": 32,
      "scale": 0,
      "postgresql": {
        "columnName": "id_inscripcion_curso",
        "dataType": "integer",
        "dataLength": null,
        "dataPrecision": 32,
        "dataScale": 0,
        "nullable": "YES"
      },
      "_selectable": true
    },
    "preg1": {
      "type": "String",
      "required": false,
      "length": 1,
      "precision": null,
      "scale": null,
      "postgresql": {
        "columnName": "preg1",
        "dataType": "character",
        "dataLength": 1,
        "dataPrecision": null,
        "dataScale": null,
        "nullable": "YES"
      },
      "_selectable": true
    },
    "preg2": {
      "type": "String",
      "required": false,
      "length": 1,
      "precision": null,
      "scale": null,
      "postgresql": {
        "columnName": "preg2",
        "dataType": "character",
        "dataLength": 1,
        "dataPrecision": null,
        "dataScale": null,
        "nullable": "YES"
      },
      "_selectable": true
    },
    "preg3": {
      "type": "String",
      "required": false,
      "length": 1,
      "precision": null,
      "scale": null,
      "postgresql": {
        "columnName": "preg3",
        "dataType": "character",
        "dataLength": 1,
        "dataPrecision": null,
        "dataScale": null,
        "nullable": "YES"
      },
      "_selectable": true
    },
    "preg4": {
      "type": "String",
      "required": false,
      "length": 1,
      "precision": null,
      "scale": null,
      "postgresql": {
        "columnName": "preg4",
        "dataType": "character",
        "dataLength": 1,
        "dataPrecision": null,
        "dataScale": null,
        "nullable": "YES"
      },
      "_selectable": true
    },
    "preg5": {
      "type": "String",
      "required": false,
      "length": 1,
      "precision": null,
      "scale": null,
      "postgresql": {
        "columnName": "preg5",
        "dataType": "character",
        "dataLength": 1,
        "dataPrecision": null,
        "dataScale": null,
        "nullable": "YES"
      },
      "_selectable": true
    },
    "preg6": {
      "type": "String",
      "required": false,
      "length": 1,
      "precision": null,
      "scale": null,
      "postgresql": {
        "columnName": "preg6",
        "dataType": "character",
        "dataLength": 1,
        "dataPrecision": null,
        "dataScale": null,
        "nullable": "YES"
      },
      "_selectable": true
    },
    "preg7": {
      "type": "String",
      "required": false,
      "length": 1,
      "precision": null,
      "scale": null,
      "postgresql": {
        "columnName": "preg7",
        "dataType": "character",
        "dataLength": 1,
        "dataPrecision": null,
        "dataScale": null,
        "nullable": "YES"
      },
      "_selectable": true
    },
    "preg8": {
      "type": "String",
      "required": false,
      "length": 1,
      "precision": null,
      "scale": null,
      "postgresql": {
        "columnName": "preg8",
        "dataType": "character",
        "dataLength": 1,
        "dataPrecision": null,
        "dataScale": null,
        "nullable": "YES"
      },
      "_selectable": true
    },
    "preg9": {
      "type": "String",
      "required": false,
      "length": 1,
      "precision": null,
      "scale": null,
      "postgresql": {
        "columnName": "preg9",
        "dataType": "character",
        "dataLength": 1,
        "dataPrecision": null,
        "dataScale": null,
        "nullable": "YES"
      },
      "_selectable": true
    },
    "preg10": {
      "type": "String",
      "required": false,
      "length": 1,
      "precision": null,
      "scale": null,
      "postgresql": {
        "columnName": "preg10",
        "dataType": "character",
        "dataLength": 1,
        "dataPrecision": null,
        "dataScale": null,
        "nullable": "YES"
      },
      "_selectable": true
    },
    "preg11": {
      "type": "String",
      "required": false,
      "length": 1,
      "precision": null,
      "scale": null,
      "postgresql": {
        "columnName": "preg11",
        "dataType": "character",
        "dataLength": 1,
        "dataPrecision": null,
        "dataScale": null,
        "nullable": "YES"
      },
      "_selectable": true
    },
    "preg12": {
      "type": "String",
      "required": false,
      "length": 1,
      "precision": null,
      "scale": null,
      "postgresql": {
        "columnName": "preg12",
        "dataType": "character",
        "dataLength": 1,
        "dataPrecision": null,
        "dataScale": null,
        "nullable": "YES"
      },
      "_selectable": true
    },
    "preg13": {
      "type": "String",
      "required": false,
      "length": 1,
      "precision": null,
      "scale": null,
      "postgresql": {
        "columnName": "preg13",
        "dataType": "character",
        "dataLength": 1,
        "dataPrecision": null,
        "dataScale": null,
        "nullable": "YES"
      },
      "_selectable": true
    },
    "preg14": {
      "type": "String",
      "required": false,
      "length": null,
      "precision": null,
      "scale": null,
      "postgresql": {
        "columnName": "preg14",
        "dataType": "text",
        "dataLength": null,
        "dataPrecision": null,
        "dataScale": null,
        "nullable": "YES"
      },
      "_selectable": true
    },
    "comentarios": {
      "type": "String",
      "required": false,
      "length": null,
      "precision": null,
      "scale": null,
      "postgresql": {
        "columnName": "comentarios",
        "dataType": "text",
        "dataLength": null,
        "dataPrecision": null,
        "dataScale": null,
        "nullable": "YES"
      },
      "_selectable": true
    },
    "origen": {
      "type": "Number",
      "required": false,
      "length": null,
      "precision": 16,
      "scale": 0,
      "postgresql": {
        "columnName": "origen",
        "dataType": "smallint",
        "dataLength": null,
        "dataPrecision": 16,
        "dataScale": 0,
        "nullable": "YES"
      },
      "_selectable": true
    }
  },
  "validations": [],
  "relations": {},
  "acls": [],
  "methods": {}
}
